kumoai/__init__.py
kumoai/client.py
kumoai/datamodel/__init__.py
kumoai/datamodel/data_source.py
kumoai/datamodel/jobs.py
kumoai/datamodel/json_serde.py
kumoai/datamodel/pquery.py
kumoai/examples/__init__.py
kumoai/examples/financial.py
kumoai/examples/orchestration.py
kumoai/examples/save_load_modify_pquery.py
kumo_ai-0.1.11.dist-info/LICENSE
kumo_ai-0.1.11.dist-info/METADATA
kumo_ai-0.1.11.dist-info/WHEEL
kumo_ai-0.1.11.dist-info/top_level.txt
kumo_ai-0.1.11.dist-info/RECORD
