Metadata-Version: 2.1
Name: kumo-ai
Version: 0.1.11
Summary: Kumo.ai Client SDK
Home-page: https://kumo.ai
Author: Kumo.ai
Author-email: support@kumo.ai
License: MIT
Keywords: kumo
Classifier: Development Status :: 3 - Alpha
Classifier: Intended Audience :: Developers
Classifier: License :: OSI Approved :: MIT License
Classifier: Programming Language :: Python :: 3
Requires-Python: >=3.8
License-File: LICENSE
Requires-Dist: pydantic (==1.10.4)
Requires-Dist: requests (==2.28.2)
